visnet1d/__init__.py
visnet1d/layout.py
visnet1d/site.py
visnet1d-0.1.4.dist-info/LICENSE
visnet1d-0.1.4.dist-info/METADATA
visnet1d-0.1.4.dist-info/WHEEL
visnet1d-0.1.4.dist-info/RECORD
