Metadata-Version: 2.1
Name: visnet1d
Version: 0.1.4
Summary: A visualation tool for 1D networks
Home-page: https://gitlab.com/abdrysdale/visnet1d
License: GPLv3+
Author: Alex
Author-email: adrysdale@protonmail.com
Requires-Python: >=3.10,<4.0
Classifier: License :: Other/Proprietary License
Classifier: Programming Language :: Python :: 3
Classifier: Programming Language :: Python :: 3.10
Classifier: Programming Language :: Python :: 3.11
Requires-Dist: dash (>=2.3.1,<3.0.0)
Requires-Dist: numpy (>=1.22.3,<2.0.0)
Requires-Dist: pandas (>=1.4.2,<2.0.0)
Requires-Dist: pillow (>=9.4.0,<10.0.0)
Requires-Dist: plotly (>=5.7.0,<6.0.0)
Project-URL: Repository, https://gitlab.com/abdrysdale/visnet1d
